dms_annotator/__init__.py
dms_annotator/dist/assets/index-8xjrpO5j.js
dms_annotator/dist/assets/index-V8MuixH_.css
dms_annotator/dist/favicon.jpg
dms_annotator/dist/favicon.svg
dms_annotator/dist/index.html
dms_annotator/main.py
dms_annotator/tools.py
dms_annotator-0.0.6.dist-info/METADATA
dms_annotator-0.0.6.dist-info/WHEEL
dms_annotator-0.0.6.dist-info/entry_points.txt
dms_annotator-0.0.6.dist-info/RECORD
