Metadata-Version: 2.1
Name: dms-annotator
Version: 0.0.6
Summary: 
Author: Gilad Kutiel
Author-email: giladk@mobileye.com
Requires-Python: >=3.10,<4.0
Classifier: Programming Language :: Python :: 3
Classifier: Programming Language :: Python :: 3.10
Classifier: Programming Language :: Python :: 3.11
Requires-Dist: fastapi (>=0.109.0,<0.110.0)
Requires-Dist: fire (>=0.5.0,<0.6.0)
Requires-Dist: opencv-python (>=4.5.5.64,<5.0.0.0)
Requires-Dist: pillow (>=10.2.0,<11.0.0)
Requires-Dist: tqdm (>=4.66.1,<5.0.0)
Requires-Dist: ultralight (>=2.2.0,<3.0.0)
Requires-Dist: uvicorn[standard] (>=0.27.0.post1,<0.28.0)
